LICENSE
MANIFEST.in
README.rst
setup.py
django_fileflatpages.egg-info/PKG-INFO
django_fileflatpages.egg-info/SOURCES.txt
django_fileflatpages.egg-info/dependency_links.txt
django_fileflatpages.egg-info/requires.txt
django_fileflatpages.egg-info/top_level.txt
example_project/__init__.py
example_project/manage.py
example_project/requirements.txt
example_project/settings.py
example_project/urls.py
example_project/app/__init__.py
example_project/app/models.py
example_project/app/tests.py
example_project/app/views.py
example_project/app/flatpages/about.rst
example_project/app/flatpages/index.rst
example_project/app/flatpages/test.html
example_project/app/templates/flatpages/default.html
example_project/app/templates/flatpages/rst.html
fileflatpages/__init__.py
fileflatpages/models.py
fileflatpages/tests.py
fileflatpages/views.py
fileflatpages/management/__init__.py
fileflatpages/management/commands/__init__.py
fileflatpages/management/commands/loadflatpages.py