Metadata-Version: 1.0
Name: django-fileflatpages
Version: 0.1
Summary: Django App for storing FlatPage fixtures per file.
Home-page: https://bitbucket.org/keegan_csmith/django-fileflatpages
Author: Keegan Carruthers-Smith
Author-email: keegan.csmith@gmail.com
License: UNKNOWN
Platform: UNKNOWN
Classifier: Development Status :: 3 - Alpha
Classifier: Framework :: Django
Classifier: Intended Audience :: Developers
Classifier: License :: OSI Approved :: BSD License
Classifier: Operating System :: OS Independent
Classifier: Programming Language :: Python
Classifier: Topic :: Software Development
